langgate/server/__init__.py
langgate/server/main.py
langgate/server/py.typed
langgate/server/api/__init__.py
langgate/server/api/api_v1/__init__.py
langgate/server/api/api_v1/api.py
langgate/server/api/api_v1/endpoints/__init__.py
langgate/server/api/api_v1/endpoints/models_ep.py
langgate/server/api/services/__init__.py
langgate/server/api/services/registry_api.py
langgate/server/core/__init__.py
langgate/server/core/config.py
langgate/server/core/logging.py
langgate_server-0.3.3.dist-info/METADATA
langgate_server-0.3.3.dist-info/WHEEL
langgate_server-0.3.3.dist-info/RECORD
