Metadata-Version: 2.4
Name: langgate-server
Version: 0.3.3
Summary: Server implementation for LangGate AI Gateway
Author: Tanantor Ltd.
Maintainer-email: Saran Connoly <saran@tanantor.com>
License: MIT
Requires-Python: >=3.13
Requires-Dist: fastapi<0.116.0,>=0.115.11
Requires-Dist: langgate-core==0.3.3
Requires-Dist: langgate-registry==0.3.3
Requires-Dist: pydantic-settings<3.0.0,>=2.8.1
Requires-Dist: pyyaml<7.0.0,>=6.0.1
Requires-Dist: uvicorn[standard]<0.35.0,>=0.34.0
